miros_rabbitmq/__init__.py
miros_rabbitmq/cache.py
miros_rabbitmq/network.py
miros_rabbitmq-0.2.0.dist-info/DESCRIPTION.rst
miros_rabbitmq-0.2.0.dist-info/METADATA
miros_rabbitmq-0.2.0.dist-info/RECORD
miros_rabbitmq-0.2.0.dist-info/WHEEL
miros_rabbitmq-0.2.0.dist-info/metadata.json
miros_rabbitmq-0.2.0.dist-info/top_level.txt
