Metadata-Version: 2.0
Name: miros-rabbitmq
Version: 0.2.0
Summary: A rabbitmq network support library for miros
Home-page: https://github.com/aleph2c/miros-rabbitmq
Author: Scott Volk
Author-email: scottvolk@gmail.com
License: Python 3.5 license
Keywords: iot hsm HSM statechart hierarchical state machine statemachine miros pika rabbitmq netifaces cryptography botnet
Platform: UNKNOWN
Classifier: Development Status :: 4 - Beta
Classifier: Intended Audience :: Developers
Classifier: Topic :: Software Development :: Build Tools
Classifier: License :: OSI Approved :: Python Software Foundation License
Classifier: Programming Language :: Python :: 3.5
Classifier: Programming Language :: Python :: 3.6
Classifier: Programming Language :: Python :: 3.7
Requires-Dist: pika
Requires-Dist: miros
Requires-Dist: netifaces
Requires-Dist: cryptography
Requires-Dist: python-dotenv
